<?xml version="1.0" encoding="UTF-8"?>
<actions>
        <action>
            <actionName>run</actionName>
            <packagings>
                <packaging>hpi</packaging>
            </packagings>
            <goals>
                <goal>hpi:run</goal>
            </goals>
            <properties>
                <jetty.port>8090</jetty.port>
            </properties>
        </action>
        <action>
            <actionName>CUSTOM-deploy</actionName>
            <displayName>deploy</displayName>
            <goals>
                <goal>deploy</goal>
            </goals>
        </action>
        <action>
            <actionName>CUSTOM-Rollback Release</actionName>
            <displayName>Rollback Release</displayName>
            <goals>
                <goal>release:rollback</goal>
            </goals>
        </action>
        <action>
            <actionName>CUSTOM-Clean Release</actionName>
            <displayName>Clean Release</displayName>
            <goals>
                <goal>release:clean</goal>
            </goals>
        </action>
        <action>
            <actionName>CUSTOM-Release Plugin</actionName>
            <displayName>Clean Release</displayName>
            <goals>
                <goal>release:prepare</goal>
                <goal>release:perform</goal>
            </goals>
        </action>
    </actions>
